eeg_ml_pipeline/__init__.py
eeg_ml_pipeline/config.py
eeg_ml_pipeline/entropy_features.py
eeg_ml_pipeline/feature_extraction.py
eeg_ml_pipeline/fractal_dimensions_features.py
eeg_ml_pipeline/frequency_features.py
eeg_ml_pipeline/model_training.py
eeg_ml_pipeline/pipeline.py
eeg_ml_pipeline/time_features.py
eeg_ml_pipeline/utils.py
eeg_ml_pipeline/visualization.py
eeg_ml_pipeline/wavelet_features.py
eeg_ml_pipeline-0.4.dist-info/LICENSE
eeg_ml_pipeline-0.4.dist-info/METADATA
eeg_ml_pipeline-0.4.dist-info/WHEEL
eeg_ml_pipeline-0.4.dist-info/top_level.txt
eeg_ml_pipeline-0.4.dist-info/RECORD
